<?xml version="1.0" encoding="UTF-8"?>
<flow xmlns="http://www.springframework.org/schema/webflow"
      xmlns:xsi="http://www.w3.org/2001/XMLSchema-instance"
      xsi:schemaLocation="http://www.springframework.org/schema/webflow
                          http://www.springframework.org/schema/webflow/spring-webflow-1.0.xsd">

    <input-mapper>
        <mapping source="space" target="flowScope.space"/>
    </input-mapper>    
    
    <start-state idref="spaceAllocate"/>   
    
    <view-state id="spaceAllocate" view="space_allocate">
        <entry-actions>
            <action bean="spaceFormAction" method="spaceAllocateSetup"/>
        </entry-actions>
        <transition on="allocate" to="spaceAllocate">
            <action bean="spaceFormAction" method="spaceAllocateHandler"/>
        </transition>
        <transition on="deallocate" to="spaceAllocate">
            <action bean="spaceFormAction" method="spaceDeallocateHandler"/>
        </transition>     
        <transition on="cancel" to="spaceListView"/>
        <transition on="userCreate" to="userForm"/>
    </view-state>   

    <subflow-state id="userForm" flow="user">
        <attribute-mapper>
            <input-mapper>
                <mapping source="flowScope.space" target="space"/>
            </input-mapper>
        </attribute-mapper>
        <transition on="userListView" to="spaceAllocate"/>
    </subflow-state>       
    
    <end-state id="spaceListView" view="externalRedirect:/app/space_list.htm"/>

    
</flow>

